rtcat_sphinx_theme/__init__.py
rtcat_sphinx_theme/breadcrumbs.html
rtcat_sphinx_theme/footer.html
rtcat_sphinx_theme/layout.html
rtcat_sphinx_theme/layout_old.html
rtcat_sphinx_theme/search.html
rtcat_sphinx_theme/searchbox.html
rtcat_sphinx_theme/theme.conf
rtcat_sphinx_theme/versions.html
rtcat_sphinx_theme/static/css/badge_only.css
rtcat_sphinx_theme/static/css/theme.css
rtcat_sphinx_theme/static/fonts/Inconsolata-Bold.ttf
rtcat_sphinx_theme/static/fonts/Inconsolata-Regular.ttf
rtcat_sphinx_theme/static/fonts/Lato-Bold.ttf
rtcat_sphinx_theme/static/fonts/Lato-Regular.ttf
rtcat_sphinx_theme/static/fonts/RobotoSlab-Bold.ttf
rtcat_sphinx_theme/static/fonts/RobotoSlab-Regular.ttf
rtcat_sphinx_theme/static/fonts/fontawesome-webfont.eot
rtcat_sphinx_theme/static/fonts/fontawesome-webfont.svg
rtcat_sphinx_theme/static/fonts/fontawesome-webfont.ttf
rtcat_sphinx_theme/static/fonts/fontawesome-webfont.woff
rtcat_sphinx_theme/static/js/modernizr.min.js
rtcat_sphinx_theme/static/js/theme.js
rtcat_sphinx_theme-0.1.1.dist-info/DESCRIPTION.rst
rtcat_sphinx_theme-0.1.1.dist-info/METADATA
rtcat_sphinx_theme-0.1.1.dist-info/RECORD
rtcat_sphinx_theme-0.1.1.dist-info/WHEEL
rtcat_sphinx_theme-0.1.1.dist-info/metadata.json
rtcat_sphinx_theme-0.1.1.dist-info/top_level.txt
