Metadata-Version: 1.1
Name: rtcat-sphinx-theme
Version: 0.1.1
Summary:  Sphinx theme for http://docs.shishimao.com/
Home-page: https://github.com/RTCat/rtcat_sphinx_theme.git
Author: Dave Snider, RealTimeCat
Author-email: dave.snider@gmail.com, info@learning-tech.com
License: MIT
Platform: UNKNOWN
Classifier: Development Status :: 3 - Alpha
Classifier: License :: OSI Approved :: BSD License
Classifier: Environment :: Console
Classifier: Environment :: Web Environment
Classifier: Intended Audience :: Developers
Classifier: Programming Language :: Python :: 2.7
Classifier: Programming Language :: Python :: 3
Classifier: Operating System :: OS Independent
Classifier: Topic :: Documentation
Classifier: Topic :: Software Development :: Documentation
